
main <test.lua:0,0> (15 instructions at 0000000000180370)
0+ params, 5 slots, 1 upvalue, 0 locals, 7 constants, 2 functions
	1	[9]	CLOSURE  	0 0	; 0000000000180640
	2	[2]	SETTABUP 	0 -1 0	; _ENV "max"
	3	[14]	CLOSURE  	0 1	; 00000000001809C0
	4	[12]	SETTABUP 	0 -2 0	; _ENV "add"
	5	[16]	GETTABUP 	0 0 -3	; _ENV "console"
	6	[16]	LOADK    	1 -4	; "hello world"
	7	[16]	CALL     	0 2 1
	8	[17]	GETTABUP 	0 0 -3	; _ENV "console"
	9	[17]	LOADK    	1 -5	; "max "
	10	[17]	GETTABUP 	2 0 -1	; _ENV "max"
	11	[17]	LOADK    	3 -6	; 10
	12	[17]	LOADK    	4 -7	; 8
	13	[17]	CALL     	2 3 0
	14	[17]	CALL     	0 0 1
	15	[17]	RETURN   	0 1

function <test.lua:2,9> (8 instructions at 0000000000180640)
2 params, 3 slots, 1 upvalue, 2 locals, 1 constant, 0 functions
	1	[3]	LT       	0 1 0
	2	[3]	JMP      	0 2	; to 5
	3	[4]	SETTABUP 	0 -1 0	; _ENV "r"
	4	[4]	JMP      	0 1	; to 6
	5	[6]	SETTABUP 	0 -1 1	; _ENV "r"
	6	[8]	GETTABUP 	2 0 -1	; _ENV "r"
	7	[8]	RETURN   	2 2
	8	[9]	RETURN   	0 1

function <test.lua:12,14> (3 instructions at 00000000001809C0)
2 params, 3 slots, 0 upvalues, 2 locals, 0 constants, 0 functions
	1	[13]	ADD      	2 0 1
	2	[13]	RETURN   	2 2
	3	[14]	RETURN   	0 1
